model_runner/__init__.py
model_runner/grpc/__init__.py
model_runner/grpc/generated/__init__.py
model_runner/grpc/generated/__init__.pyi
model_runner/grpc/generated/commons_pb2.py
model_runner/grpc/generated/commons_pb2.pyi
model_runner/grpc/generated/commons_pb2_grpc.py
model_runner/grpc/generated/dynamic_subclass_pb2.py
model_runner/grpc/generated/dynamic_subclass_pb2.pyi
model_runner/grpc/generated/dynamic_subclass_pb2_grpc.py
model_runner/grpc/generated/train_infer_pb2.py
model_runner/grpc/generated/train_infer_pb2.pyi
model_runner/grpc/generated/train_infer_pb2_grpc.py
model_runner/grpc/protos/__init__.py
model_runner/grpc/protos/commons.proto
model_runner/grpc/protos/dynamic_subclass.proto
model_runner/grpc/protos/train_infer.proto
model_runner/server.py
model_runner/servicers/__init__.py
model_runner/servicers/dynamic_subclass_servicer.py
model_runner/servicers/exclusive_service_mixin.py
model_runner/servicers/train_infer_servicer.py
model_runner/utils/__init__.py
model_runner/utils/checkers.py
model_runner/utils/class_resolver.py
model_runner/utils/datatype_transformer.py
crunch_model_runner-0.4.1.dist-info/METADATA
crunch_model_runner-0.4.1.dist-info/WHEEL
crunch_model_runner-0.4.1.dist-info/entry_points.txt
crunch_model_runner-0.4.1.dist-info/RECORD
